{
	"name": "Notebook 1",
	"properties": {
		"nbformat": 4,
		"nbformat_minor": 2,
		"bigDataPool": {
			"referenceName": "sparkpool01",
			"type": "BigDataPoolReference"
		},
		"sessionProperties": {
			"driverMemory": "56g",
			"driverCores": 8,
			"executorMemory": "56g",
			"executorCores": 8,
			"numExecutors": 1,
			"conf": {
				"spark.dynamicAllocation.enabled": "true",
				"spark.dynamicAllocation.minExecutors": "1",
				"spark.dynamicAllocation.maxExecutors": "9",
				"spark.autotune.trackingId": "0f4c6fd1-39a3-4b6b-878c-3c314527ac9e"
			}
		},
		"metadata": {
			"saveOutput": true,
			"enableDebugMode": false,
			"kernelspec": {
				"name": "synapse_pyspark",
				"display_name": "python"
			},
			"language_info": {
				"name": "python"
			},
			"a365ComputeOptions": {
				"id": "/subscriptions/5dbd4eba-831b-499f-ac29-f8034f97fb9d/resourceGroups/rgpocsefazballkms/providers/Microsoft.Synapse/workspaces/wspocsefazballkms/bigDataPools/sparkpool01",
				"name": "sparkpool01",
				"type": "Spark",
				"endpoint": "https://wspocsefazballkms.dev.azuresynapse.net/livyApi/versions/2019-11-01-preview/sparkPools/sparkpool01",
				"auth": {
					"type": "AAD",
					"authResource": "https://dev.azuresynapse.net"
				},
				"sparkVersion": "3.2",
				"nodeCount": 10,
				"cores": 8,
				"memory": 56,
				"automaticScaleJobs": true
			},
			"sessionKeepAliveTimeout": 30
		},
		"cells": [
			{
				"cell_type": "code",
				"metadata": {
					"microsoft": {
						"language": "python"
					}
				},
				"source": [
					"%%pyspark\n",
					"df = spark.sql(\"SELECT * FROM `LakeDatabase1`.`csv_poc_ms_amostra_dataset_2022_08_22_V7`\")\n",
					"# df.show(10)"
				],
				"execution_count": null
			}
		]
	}
}